odoo/addons/partner_email_check/README.rst
odoo/addons/partner_email_check/__init__.py
odoo/addons/partner_email_check/__manifest__.py
odoo/addons/partner_email_check/demo/res_company_demo.xml
odoo/addons/partner_email_check/i18n/partner_email_check.pot
odoo/addons/partner_email_check/models/__init__.py
odoo/addons/partner_email_check/models/res_company.py
odoo/addons/partner_email_check/models/res_config_settings.py
odoo/addons/partner_email_check/models/res_partner.py
odoo/addons/partner_email_check/readme/CONFIGURE.rst
odoo/addons/partner_email_check/readme/CONTRIBUTORS.rst
odoo/addons/partner_email_check/readme/DESCRIPTION.rst
odoo/addons/partner_email_check/readme/USAGE.rst
odoo/addons/partner_email_check/static/description/icon.png
odoo/addons/partner_email_check/static/description/index.html
odoo/addons/partner_email_check/tests/__init__.py
odoo/addons/partner_email_check/tests/test_partner_email_check.py
odoo/addons/partner_email_check/views/base_config_view.xml
odoo14_addon_partner_email_check-14.0.1.1.1.dist-info/METADATA
odoo14_addon_partner_email_check-14.0.1.1.1.dist-info/WHEEL
odoo14_addon_partner_email_check-14.0.1.1.1.dist-info/top_level.txt
odoo14_addon_partner_email_check-14.0.1.1.1.dist-info/RECORD
